{
    "asset": {
        "format": "png",
        "id": "72176f088c776415404e2cd31b674e19",
        "name": "i418.png",
        "path": "file:/home/ronit/Training_Images/i418.png",
        "size": {
            "width": 696,
            "height": 464
        },
        "state": 2,
        "type": 1
    },
    "regions": [
        {
            "id": "IDJS5kPLN",
            "type": "RECTANGLE",
            "tags": [
                "License_plate"
            ],
            "boundingBox": {
                "height": 59.66986564299424,
                "width": 113.923273657289,
                "left": 292.81841432225065,
                "top": 320.3219769673704
            },
            "points": [
                {
                    "x": 292.81841432225065,
                    "y": 320.3219769673704
                },
                {
                    "x": 406.7416879795396,
                    "y": 320.3219769673704
                },
                {
                    "x": 406.7416879795396,
                    "y": 379.99184261036464
                },
                {
                    "x": 292.81841432225065,
                    "y": 379.99184261036464
                }
            ]
        }
    ],
    "version": "2.2.0"
}