{
    "asset": {
        "format": "png",
        "id": "87f95a64b597c9b29f14a653a7900559",
        "name": "i328.png",
        "path": "file:/home/ronit/Training_Images/i328.png",
        "size": {
            "width": 940,
            "height": 730
        },
        "state": 2,
        "type": 1
    },
    "regions": [
        {
            "id": "0WXCxzDjk",
            "type": "RECTANGLE",
            "tags": [
                "License_plate"
            ],
            "boundingBox": {
                "height": 86.17637973640858,
                "width": 260.843989769821,
                "left": 367.82608695652175,
                "top": 430.5436573311368
            },
            "points": [
                {
                    "x": 367.82608695652175,
                    "y": 430.5436573311368
                },
                {
                    "x": 628.6700767263427,
                    "y": 430.5436573311368
                },
                {
                    "x": 628.6700767263427,
                    "y": 516.7200370675454
                },
                {
                    "x": 367.82608695652175,
                    "y": 516.7200370675454
                }
            ]
        }
    ],
    "version": "2.2.0"
}