{
    "asset": {
        "format": "png",
        "id": "d3cc9680d8fce09ce1bed41dd7bb6389",
        "name": "i269.png",
        "path": "file:/home/ronit/Training_Images/i269.png",
        "size": {
            "width": 274,
            "height": 184
        },
        "state": 2,
        "type": 1
    },
    "regions": [
        {
            "id": "smNTlOwDM",
            "type": "RECTANGLE",
            "tags": [
                "License_plate"
            ],
            "boundingBox": {
                "height": 15.771428571428572,
                "width": 22.424552429667518,
                "left": 40.644501278772374,
                "top": 81.51309523809525
            },
            "points": [
                {
                    "x": 40.644501278772374,
                    "y": 81.51309523809525
                },
                {
                    "x": 63.069053708439895,
                    "y": 81.51309523809525
                },
                {
                    "x": 63.069053708439895,
                    "y": 97.28452380952382
                },
                {
                    "x": 40.644501278772374,
                    "y": 97.28452380952382
                }
            ]
        }
    ],
    "version": "2.2.0"
}