{
    "asset": {
        "format": "png",
        "id": "eb53caf93b5a7fbc0df41c7bc323b50e",
        "name": "i358.png",
        "path": "file:/home/ronit/Training_Images/i358.png",
        "size": {
            "width": 225,
            "height": 225
        },
        "state": 2,
        "type": 1
    },
    "regions": [
        {
            "id": "8KNoDXy8N",
            "type": "RECTANGLE",
            "tags": [
                "License_plate"
            ],
            "boundingBox": {
                "height": 30.453821656050952,
                "width": 55.53343949044586,
                "left": 164.45063694267515,
                "top": 173.76592356687897
            },
            "points": [
                {
                    "x": 164.45063694267515,
                    "y": 173.76592356687897
                },
                {
                    "x": 219.984076433121,
                    "y": 173.76592356687897
                },
                {
                    "x": 219.984076433121,
                    "y": 204.21974522292993
                },
                {
                    "x": 164.45063694267515,
                    "y": 204.21974522292993
                }
            ]
        }
    ],
    "version": "2.2.0"
}