{
    "asset": {
        "format": "png",
        "id": "066a8dc2fb6a5b7ce98fe0b0c1cfb3c8",
        "name": "i129.png",
        "path": "file:/home/ronit/Training_Images/i129.png",
        "size": {
            "width": 605,
            "height": 671
        },
        "state": 2,
        "type": 1
    },
    "regions": [
        {
            "id": "OhJhbtLmu",
            "type": "RECTANGLE",
            "tags": [
                "License_plate"
            ],
            "boundingBox": {
                "height": 50.218152866242036,
                "width": 120.65260600706715,
                "left": 222.46576855123675,
                "top": 306.6512738853503
            },
            "points": [
                {
                    "x": 222.46576855123675,
                    "y": 306.6512738853503
                },
                {
                    "x": 343.1183745583039,
                    "y": 306.6512738853503
                },
                {
                    "x": 343.1183745583039,
                    "y": 356.86942675159236
                },
                {
                    "x": 222.46576855123675,
                    "y": 356.86942675159236
                }
            ]
        }
    ],
    "version": "2.2.0"
}