{
    "asset": {
        "format": "png",
        "id": "13f8946ed4f71c87fe376795b0a1fb9e",
        "name": "i189.png",
        "path": "file:/home/ronit/Training_Images/i189.png",
        "size": {
            "width": 609,
            "height": 457
        },
        "state": 2,
        "type": 1
    },
    "regions": [
        {
            "id": "6eXX0nLwT",
            "type": "RECTANGLE",
            "tags": [
                "License Plate"
            ],
            "boundingBox": {
                "height": 145.58603066439525,
                "width": 272.5703324808184,
                "left": 164.32097186700767,
                "top": 221.43236264906304
            },
            "points": [
                {
                    "x": 164.32097186700767,
                    "y": 221.43236264906304
                },
                {
                    "x": 436.8913043478261,
                    "y": 221.43236264906304
                },
                {
                    "x": 436.8913043478261,
                    "y": 367.01839331345826
                },
                {
                    "x": 164.32097186700767,
                    "y": 367.01839331345826
                }
            ]
        }
    ],
    "version": "2.2.0"
}