{
    "asset": {
        "format": "png",
        "id": "3b3776c9b69e0ec397f60074071c5b1b",
        "name": "i207.png",
        "path": "file:/home/ronit/Training_Images/i207.png",
        "size": {
            "width": 1024,
            "height": 763
        },
        "state": 2,
        "type": 1
    },
    "regions": [
        {
            "id": "OlU0G3qWB",
            "type": "RECTANGLE",
            "tags": [
                "License_plate"
            ],
            "boundingBox": {
                "height": 53.65866209262436,
                "width": 170.230179028133,
                "left": 373.1969309462916,
                "top": 500.3915630360206
            },
            "points": [
                {
                    "x": 373.1969309462916,
                    "y": 500.3915630360206
                },
                {
                    "x": 543.4271099744246,
                    "y": 500.3915630360206
                },
                {
                    "x": 543.4271099744246,
                    "y": 554.0502251286449
                },
                {
                    "x": 373.1969309462916,
                    "y": 554.0502251286449
                }
            ]
        },
        {
            "id": "mIHZA8NGE",
            "type": "RECTANGLE",
            "tags": [
                "License_plate"
            ],
            "boundingBox": {
                "height": 24.866209262435678,
                "width": 28.80818414322251,
                "left": 620.6854219948849,
                "top": 404.8529695540309
            },
            "points": [
                {
                    "x": 620.6854219948849,
                    "y": 404.8529695540309
                },
                {
                    "x": 649.4936061381075,
                    "y": 404.8529695540309
                },
                {
                    "x": 649.4936061381075,
                    "y": 429.7191788164666
                },
                {
                    "x": 620.6854219948849,
                    "y": 429.7191788164666
                }
            ]
        }
    ],
    "version": "2.2.0"
}