{
    "asset": {
        "format": "png",
        "id": "8e080dcfd9aa5188be682275a1b03643",
        "name": "i315.png",
        "path": "file:/home/ronit/Training_Images/i315.png",
        "size": {
            "width": 1024,
            "height": 1024
        },
        "state": 2,
        "type": 1
    },
    "regions": [
        {
            "id": "0OFjn3QM4",
            "type": "RECTANGLE",
            "tags": [
                "License Plate"
            ],
            "boundingBox": {
                "height": 50.547770700636946,
                "width": 185.88535031847135,
                "left": 141.85987261146497,
                "top": 772.891719745223
            },
            "points": [
                {
                    "x": 141.85987261146497,
                    "y": 772.891719745223
                },
                {
                    "x": 327.74522292993635,
                    "y": 772.891719745223
                },
                {
                    "x": 327.74522292993635,
                    "y": 823.4394904458599
                },
                {
                    "x": 141.85987261146497,
                    "y": 823.4394904458599
                }
            ]
        }
    ],
    "version": "2.2.0"
}