{
    "asset": {
        "format": "png",
        "id": "94ab5ff50131860f37013e9b6074b67b",
        "name": "i305.png",
        "path": "file:/home/ronit/Training_Images/i305.png",
        "size": {
            "width": 599,
            "height": 400
        },
        "state": 2,
        "type": 1
    },
    "regions": [
        {
            "id": "g-EVO44a1",
            "type": "RECTANGLE",
            "tags": [
                "License_plate"
            ],
            "boundingBox": {
                "height": 183.9080459770115,
                "width": 303.3299232736573,
                "left": 155.49488491048595,
                "top": 216.09195402298852
            },
            "points": [
                {
                    "x": 155.49488491048595,
                    "y": 216.09195402298852
                },
                {
                    "x": 458.82480818414325,
                    "y": 216.09195402298852
                },
                {
                    "x": 458.82480818414325,
                    "y": 400
                },
                {
                    "x": 155.49488491048595,
                    "y": 400
                }
            ]
        }
    ],
    "version": "2.2.0"
}