{
    "asset": {
        "format": "png",
        "id": "dcfdf6e06a2f27b75911b0b0106cbdd4",
        "name": "i294.png",
        "path": "file:/home/ronit/Training_Images2/i294.png",
        "size": {
            "width": 200,
            "height": 200
        },
        "state": 2,
        "type": 1
    },
    "regions": [
        {
            "id": "VDBf7y-W_",
            "type": "RECTANGLE",
            "tags": [
                "License_Plate"
            ],
            "boundingBox": {
                "height": 30.573248407643312,
                "width": 24.203821656050955,
                "left": 73.88535031847134,
                "top": 149.68152866242036
            },
            "points": [
                {
                    "x": 73.88535031847134,
                    "y": 149.68152866242036
                },
                {
                    "x": 98.08917197452229,
                    "y": 149.68152866242036
                },
                {
                    "x": 98.08917197452229,
                    "y": 180.25477707006368
                },
                {
                    "x": 73.88535031847134,
                    "y": 180.25477707006368
                }
            ]
        }
    ],
    "version": "2.2.0"
}