{
    "asset": {
        "format": "png",
        "id": "ed46309ceb85e9a7d0ed83f0f99303f1",
        "name": "i492.png",
        "path": "file:/home/ronit/Training_Images/i492.png",
        "size": {
            "width": 269,
            "height": 188
        },
        "state": 2,
        "type": 1
    },
    "regions": [
        {
            "id": "X8AKZrU37",
            "type": "RECTANGLE",
            "tags": [
                "License_plate"
            ],
            "boundingBox": {
                "height": 15.46617915904936,
                "width": 51.94245524296675,
                "left": 49.53452685421995,
                "top": 88.42036106032907
            },
            "points": [
                {
                    "x": 49.53452685421995,
                    "y": 88.42036106032907
                },
                {
                    "x": 101.47698209718669,
                    "y": 88.42036106032907
                },
                {
                    "x": 101.47698209718669,
                    "y": 103.88654021937843
                },
                {
                    "x": 49.53452685421995,
                    "y": 103.88654021937843
                }
            ]
        }
    ],
    "version": "2.2.0"
}