{
    "asset": {
        "format": "png",
        "id": "ef77f72172ffe2ea84d223e6ceb3e671",
        "name": "i263.png",
        "path": "file:/home/ronit/Training_Images/i263.png",
        "size": {
            "width": 225,
            "height": 225
        },
        "state": 2,
        "type": 1
    },
    "regions": [
        {
            "id": "jofZWQJbw",
            "type": "RECTANGLE",
            "tags": [
                "License_plate"
            ],
            "boundingBox": {
                "height": 17.555732484076433,
                "width": 63.05732484076432,
                "left": 114.64968152866241,
                "top": 154.0605095541401
            },
            "points": [
                {
                    "x": 114.64968152866241,
                    "y": 154.0605095541401
                },
                {
                    "x": 177.70700636942675,
                    "y": 154.0605095541401
                },
                {
                    "x": 177.70700636942675,
                    "y": 171.61624203821654
                },
                {
                    "x": 114.64968152866241,
                    "y": 171.61624203821654
                }
            ]
        }
    ],
    "version": "2.2.0"
}