{
    "asset": {
        "format": "png",
        "id": "08efec701b68d94242e58840b7d92c99",
        "name": "i78.png",
        "path": "file:/home/ronit/Training_Images2/i78.png",
        "size": {
            "width": 200,
            "height": 200
        },
        "state": 2,
        "type": 1
    },
    "regions": [
        {
            "id": "pGWRdQFRl",
            "type": "RECTANGLE",
            "tags": [
                "License_Plate"
            ],
            "boundingBox": {
                "height": 114.01273885350318,
                "width": 135.66878980891718,
                "left": 7.643312101910828,
                "top": 65.28662420382166
            },
            "points": [
                {
                    "x": 7.643312101910828,
                    "y": 65.28662420382166
                },
                {
                    "x": 143.312101910828,
                    "y": 65.28662420382166
                },
                {
                    "x": 143.312101910828,
                    "y": 179.29936305732483
                },
                {
                    "x": 7.643312101910828,
                    "y": 179.29936305732483
                }
            ]
        }
    ],
    "version": "2.2.0"
}